package/__init__.py
package/main.py
find_phishing_URL-1.0.0.dist-info/LICENSE.txt
find_phishing_URL-1.0.0.dist-info/METADATA
find_phishing_URL-1.0.0.dist-info/WHEEL
find_phishing_URL-1.0.0.dist-info/entry_points.txt
find_phishing_URL-1.0.0.dist-info/top_level.txt
find_phishing_URL-1.0.0.dist-info/RECORD
