Metadata-Version: 2.1
Name: find-phishing-URL
Version: 1.0.0
Summary: An sample project which check whether the URL is phishing URL or not
Author-email: Crest Data Systems <abc@crestdatasys.com>
License: Copyright (c) 2023 Crest Data System
Project-URL: phishingURL, https://checkurl.phishtank.com/checkurl/index.php
Keywords: phishing,find_phishing_URL
Requires-Python: >=3.7
License-File: LICENSE.txt
